elia/__init__.py
elia/decorators.py
elia/elia.py
elia_py-0.3.1.dist-info/LICENSE.txt
elia_py-0.3.1.dist-info/METADATA
elia_py-0.3.1.dist-info/WHEEL
elia_py-0.3.1.dist-info/top_level.txt
elia_py-0.3.1.dist-info/RECORD
