Metadata-Version: 2.1
Name: elia-py
Version: 0.3.1
Summary: Python3 client for the webservices of Elia
Home-page: https://github.com/quintinnicolas/elia-py
Author: Nicolas Quintin
Author-email: nicolasquintin92@gmail.com
License: MIT
Classifier: Programming Language :: Python :: 3.8
Classifier: Programming Language :: Python :: 3.9
Classifier: Programming Language :: Python :: 3.10
Classifier: Programming Language :: Python :: 3.11
Classifier: Programming Language :: Python :: 3.12
Classifier: License :: OSI Approved :: MIT License
Requires-Python: >=3.8
License-File: LICENSE.txt
Requires-Dist: pandas (>=1.4.0)
Requires-Dist: typing-extensions
Requires-Dist: python-dateutil
Requires-Dist: pytz
Requires-Dist: requests
Requires-Dist: xlrd
